cram2fastq/__init__.py
cram2fastq/cram2fastq.py
cram2fastq/cramfastq.sh
cram2fastq/cramfastq_bulk.sh
cram2fastq/rename_fastq.py
cram2fastq/rename_fastq2.py
cram2fastq-0.0.5.data/data/bin/cram2fastq.py
cram2fastq-0.0.5.data/data/bin/cramfastq.sh
cram2fastq-0.0.5.data/data/bin/cramfastq_bulk.sh
cram2fastq-0.0.5.data/data/bin/rename_fastq.py
cram2fastq-0.0.5.data/data/bin/rename_fastq2.py
cram2fastq-0.0.5.dist-info/METADATA
cram2fastq-0.0.5.dist-info/WHEEL
cram2fastq-0.0.5.dist-info/top_level.txt
cram2fastq-0.0.5.dist-info/RECORD
