Metadata-Version: 2.1
Name: cram2fastq
Version: 0.0.5
Summary: Download and convert cram-to-fastq from irods.
Home-page: https://github.com/clatworthylab/cram2fastq/
Author: zktuong
Author-email: kt16@sanger.ac.uk
License: UNKNOWN
Platform: UNKNOWN
Classifier: Programming Language :: Python :: 3.7
Classifier: Programming Language :: Python :: 3.8
Classifier: Programming Language :: Python :: 3.9
Classifier: Programming Language :: Unix Shell
Requires-Dist: pandas
